Workbook

Sheet Summary
A1: ArchiAI Platform — Financial Cost Model
A2: Build Costs · Running Costs · Marketing · Break-Even Analysis
A4: KEY METRICS AT A GLANCE
A5: Metric | B5: Value | C5: Notes
A6: Total Build Cost (4 areas) | B6: ='Build Costs'!B28 | C6: Developer + API setup costs
A7: Monthly Running Cost (100 users) | B7: ='Running Costs'!B24 | C7: APIs + infra at scale
A8: Month 1 Marketing Spend | B8: ='Marketing'!B20 | C8: Launch campaign budget
A9: Break-Even Month | B9: ='Break-Even'!B16 | C9: Month when cumulative profit > 0
A10: Revenue Needed (Monthly) | B10: ='Break-Even'!B17 | C10: MRR to cover all costs
A11: Projected Month 12 Revenue | B11: ='Break-Even'!M5 | C11: 12-month revenue projection
A13: COST BREAKDOWN BY CATEGORY
A14: Category | B14: One-Time Cost | C14: Monthly Cost | D14: 3-Month Total | E14: Notes
A15: Build: Auth & Payments (Area 11) | B15: ='Build Costs'!B9 | C15: ='Running Costs'!B7 | D15: =B15+(C15*3) | E15: Clerk + Supabase + Stripe
A16: Build: LoRA Style Training (Area 7) | B16: ='Build Costs'!B14 | C16: ='Running Costs'!B10 | D16: =B16+(C16*3) | E16: Replicate API integration
A17: Build: Blender Docker (Area 6) | B17: ='Build Costs'!B19 | C17: ='Running Costs'!B13 | D17: =B17+(C17*3) | E17: Modal.com GPU renders
A18: Build: ControlNet (Area 8) | B18: ='Build Costs'!B24 | C18: ='Running Costs'!B16 | D18: =B18+(C18*3) | E18: ComfyUI + SDXL pipeline
A19: Marketing (3 months) | B19: =0 | C19: ='Marketing'!B20 | D19: =B19+(C19*3) | E19: Ads + content + outreach
A20: GRAND TOTAL (3 Months) | B20: =SUM(B15:B19) | C20: =SUM(C15:C19) | D20: =SUM(D15:D19) | E20: All inclusive

Sheet Build Costs
A1: Build Costs — 4 Remaining Pipeline Areas
A2: Rate Assumption: | B2: 45 | C2: £/hour (freelance dev rate)
A4: Area 11: Auth & Payments (Clerk + Supabase + Stripe)
A5: Task | B5: Days | C5: Hours | D5: Cost (£) | E5: Notes
A6: Clerk auth integration (sign-up, login, JWT) | B6: 3 | C6: =B6*8 | D6: =C6*$B$2 | E6: Clerk SDK, JWT middleware
A7: Supabase schema design + row-level security | B7: 2 | C7: =B7*8 | D7: =C7*$B$2 | E7: Users, designs, subscriptions tables
A8: Stripe subscription tiers (Free / Pro / Studio) | B8: 3 | C8: =B8*8 | D8: =C8*$B$2 | E8: Webhook handling, trial periods
A9: Billing portal + invoice page (React) | B9: 2 | C9: =B9*8 | D9: =C9*$B$2 | E9: Customer portal embed
A10: End-to-end auth + payment testing | B10: 2 | C10: =B10*8 | D10: =C10*$B$2 | E10: Playwright tests
A11: SUBTOTAL — Area 11 | B11: =SUM(B6:B10) | C11: =SUM(C6:C10) | D11: =SUM(D6:D10)
A13: Area 7: LoRA Style Blending (Replicate API + Style Library)
A14: Task | B14: Days | C14: Hours | D14: Cost (£) | E14: Notes
A15: Style library schema + 10 seed styles | B15: 2 | C15: =B15*8 | D15: =C15*$B$2 | E15: styleLibrary.js, JSON definitions
A16: loraTrainingService.js — trigger + poll Replicate | B16: 3 | C16: =B16*8 | D16: =C16*$B$2 | E16: Replicate API, webhook callback
A17: Portfolio upload → style extraction pipeline | B17: 3 | C17: =B17*8 | D17: =C17*$B$2 | E17: Image → LoRA training job
A18: React UI: style picker + blend slider | B18: 2 | C18: =B18*8 | D18: =C18*$B$2 | E18: ArchitectAIWizard step 4
A19: LoRA inference integration into FLUX pipeline | B19: 2 | C19: =B19*8 | D19: =C19*$B$2 | E19: loraWeightUrl injection
A20: Testing + style consistency validation | B20: 2 | C20: =B20*8 | D20: =C20*$B$2 | E20: pHash comparison
A21: SUBTOTAL — Area 7 | B21: =SUM(B15:B20) | C21: =SUM(C15:C20) | D21: =SUM(D15:D20)
A23: Area 6: Blender Docker / Modal.com GPU Renders
A24: Task | B24: Days | C24: Hours | D24: Cost (£) | E24: Notes
A25: Modal.com account setup + GPU function scaffold | B25: 1 | C25: =B25*8 | D25: =C25*$B$2 | E25: modal deploy, GPU stub
A26: Blender headless Python script (bpy render) | B26: 3 | C26: =B26*8 | D26: =C26*$B$2 | E26: Camera angles, materials, HDRI
A27: ArchiAI DNA → Blender scene builder | B27: 3 | C27: =B27*8 | D27: =C27*$B$2 | E27: DNA JSON → bpy objects
A28: api/blender-render.js service wrapper | B28: =D11+D21+D31+D41 | C28: =B28*8 | D28: =C28*$B$2 | E28: REST endpoint + polling
A29: React UI: 3D render toggle in Results step | B29: 2 | C29: =B29*8 | D29: =C29*$B$2 | E29: Async render progress bar
A30: Docker image + CI/CD deployment | B30: 1 | C30: =B30*8 | D30: =C30*$B$2 | E30: GitHub Actions → Modal
A31: SUBTOTAL — Area 6 | B31: =SUM(B25:B30) | C31: =SUM(C25:C30) | D31: =SUM(D25:D30)
A33: Area 8: ControlNet SDXL Pipeline (ComfyUI + Replicate)
A34: Task | B34: Days | C34: Hours | D34: Cost (£) | E34: Notes
A35: controlNetService.js wrapper (Canny + Depth) | B35: 2 | C35: =B35*8 | D35: =C35*$B$2 | E35: Replicate ControlNet endpoints
A36: ComfyUI workflow JSON for SDXL + ControlNet | B36: 3 | C36: =B36*8 | D36: =C36*$B$2 | E36: Canny edge, depth map conditioning
A37: Depth map extraction from Three.js geometry | B37: 2 | C37: =B37*8 | D37: =C37*$B$2 | E37: Three.js depth buffer → PNG
A38: Integration into A1 sheet generation pipeline | B38: 3 | C38: =B38*8 | D38: =C38*$B$2 | E38: Replace FLUX for technical views
A39: Quality comparison: ControlNet vs FLUX baseline | B39: 1 | C39: =B39*8 | D39: =C39*$B$2 | E39: pHash/SSIM scoring
A40: End-to-end pipeline testing | B40: 1 | C40: =B40*8 | D40: =C40*$B$2 | E40: 10 design test runs
A41: SUBTOTAL — Area 8 | B41: =SUM(B35:B40) | C41: =SUM(C35:C40) | D41: =SUM(D35:D40)
A43: TOTAL BUILD COST — ALL 4 AREAS | D43: =D11+D21+D31+D41 | E43: Complete implementation

Sheet Running Costs
A1: Monthly Running Costs — API & Infrastructure
A2: Active Users Assumption: | B2: 100 | C2: users/month (adjust B2 to scale)
A4: Service / API | B4: Cost per User/Month | C4: Monthly Total (£) | D4: Annual Total (£) | E4: Notes
A5: Together.ai — FLUX.1-dev (image gen) | B5: =0.06 | C5: =B5*$B$2 | D5: =C5*12 | E5: £0.06 per design (~3 API calls)
A6: Together.ai — Qwen 2.5-72B (reasoning) | B6: =0.02 | C6: =B6*$B$2 | D6: =C6*12 | E6: £0.02 per design (DNA gen)
A7: Together.ai — Total (subtotal) | B7: =B5+B6 | C7: =B7*$B$2 | D7: =C7*12 | E7: Sum of above
A8: Replicate — LoRA inference | B8: =0.05 | C8: =B8*$B$2 | D8: =C8*12 | E8: ~50 tokens per render
A9: Modal.com — Blender GPU renders | B9: =0.10 | C9: =B9*$B$2 | D9: =C9*12 | E9: ~5 min A100 per render
A10: Replicate — ControlNet SDXL | B10: =0.04 | C10: =B10*$B$2 | D10: =C10*12 | E10: Per technical view
A11: Google Maps API | B11: =0.005 | C11: =B11*$B$2 | D11: =C11*12 | E11: Geocoding + map tiles
A12: OpenWeather API | B12: =0.001 | C12: =B12*$B$2 | D12: =C12*12 | E12: Climate data calls
A13: Clerk — Auth | B13: =0.00 | C13: =B13*$B$2 | D13: =C13*12 | E13: Free up to 10k MAU
A14: Supabase — Database | B14: =0.025 | C14: =B14*$B$2 | D14: =C14*12 | E14: Pro plan ÷ users
A15: Vercel — Hosting | B15: =0.02 | C15: =B15*$B$2 | D15: =C15*12 | E15: Pro plan bandwidth
A16: Stripe — Payment processing | B16: =0.00 | C16: =B16*$B$2 | D16: =C16*12 | E16: 2.9%+30p per transaction (variable)
A17: TOTAL MONTHLY RUNNING COST | B17: =B5+B6+B8+B9+B10+B11+B12+B13+B14+B15+B16 | C17: =B17*$B$2 | D17: =C17*12 | E17: Per 100 active users
B24: =C17

Sheet Marketing
A1: Marketing Budget — 3-Month Launch Plan
A3: Channel | B3: Month 1 (£) | C3: Month 2 (£) | D3: Month 3 (£) | E3: Strategy
A4: Google Ads (Search) | B4: 300 | C4: 400 | D4: 500 | E4: Target: 'AI architecture tool', 'floor plan generator'
A5: LinkedIn Ads | B5: 200 | C5: 300 | D5: 350 | E5: Target: Architects, urban planners, developers
A6: Instagram / Meta Ads | B6: 150 | C6: 200 | D6: 250 | E6: Portfolio-style image carousel ads
A7: Content Creation | B7: 100 | C7: 150 | D7: 150 | E7: Blog posts, LinkedIn articles, YouTube tutorials
A8: Architecture Forum Outreach | B8: 50 | C8: 50 | D8: 50 | E8: ArchDaily, Dezeen, Reddit r/architecture
A9: Email Marketing (ConvertKit) | B9: 30 | C9: 30 | D9: 30 | E9: Nurture sequence for trial users
A10: Influencer / KOL (architects) | B10: 200 | C10: 300 | D10: 300 | E10: 2-3 architect influencers on Instagram/YouTube
A11: Free Trial Incentives | B11: 100 | C11: 100 | D11: 0 | E11: First 50 users get 5 free generations
A12: SEO / Technical content | B12: 100 | C12: 100 | D12: 50 | E12: Keyword-optimised landing pages
A13: PR / Press releases | B13: 100 | C13: 50 | D13: 50 | E13: ArchDaily, Dezeen, Wired outreach
A14: TOTAL MARKETING SPEND | B14: =SUM(B4:B13) | C14: =SUM(C4:C13) | D14: =SUM(D4:D13) | E14: =B14+C14+D14
B20: =B14

Sheet Break-Even
A1: 12-Month Break-Even Analysis
A3: PRICING ASSUMPTIONS (edit yellow cells)
A4: Free tier users | B4: 200 | C4: No revenue
A5: Pro plan users (£29/mo) | B5: 40 | C5: Main revenue driver
A6: Studio plan users (£99/mo) | B6: 8 | C6: Power users / agencies
A7: Churn rate (monthly %) | B7: 0.05 | C7: 5% monthly churn
A8: Monthly growth rate | B8: 0.15 | C8: 15% MoM user growth
B10: Month 1 | C10: Month 2 | D10: Month 3 | E10: Month 4 | F10: Month 5 | G10: Month 6 | H10: Month 7 | I10: Month 8 | J10: Month 9 | K10: Month 10 | L10: Month 11 | M10: Month 12 | N10: Total
A11: Pro Users (count) | B11: =$B$4 | C11: =B11*(1+$B$8)*(1-$B$7) | D11: =C11*(1+$B$8)*(1-$B$7) | E11: =D11*(1+$B$8)*(1-$B$7) | F11: =E11*(1+$B$8)*(1-$B$7) | G11: =F11*(1+$B$8)*(1-$B$7) | H11: =G11*(1+$B$8)*(1-$B$7) | I11: =H11*(1+$B$8)*(1-$B$7) | J11: =I11*(1+$B$8)*(1-$B$7) | ... M11: =L11*(1+$B$8)*(1-$B$7) | N11: =M11
A12: Studio Users (count) | B12: =$B$5 | C12: =B12*(1+$B$8)*(1-$B$7) | D12: =C12*(1+$B$8)*(1-$B$7) | E12: =D12*(1+$B$8)*(1-$B$7) | F12: =E12*(1+$B$8)*(1-$B$7) | G12: =F12*(1+$B$8)*(1-$B$7) | H12: =G12*(1+$B$8)*(1-$B$7) | I12: =H12*(1+$B$8)*(1-$B$7) | J12: =I12*(1+$B$8)*(1-$B$7) | ... M12: =L12*(1+$B$8)*(1-$B$7) | N12: =M12
A13: Gross Revenue (£) | B13: =ROUND(B11*29+B12*99,0) | C13: =ROUND(C11*29+C12*99,0) | D13: =ROUND(D11*29+D12*99,0) | E13: =ROUND(E11*29+E12*99,0) | F13: =ROUND(F11*29+F12*99,0) | G13: =ROUND(G11*29+G12*99,0) | H13: =ROUND(H11*29+H12*99,0) | I13: =ROUND(I11*29+I12*99,0) | ... M13: =ROUND(M11*29+M12*99,0) | N13: =SUM(B13:M13)
A14: Running Costs (£) | B14: =ROUND((B11+B12+$B$3)*0.27,0) | C14: =ROUND((C11+C12+$B$3)*0.27,0) | D14: =ROUND((D11+D12+$B$3)*0.27,0) | E14: =ROUND((E11+E12+$B$3)*0.27,0) | F14: =ROUND((F11+F12+$B$3)*0.27,0) | G14: =ROUND((G11+G12+$B$3)*0.27,0) | H14: =ROUND((H11+H12+$B$3)*0.27,0) | I14: =ROUND((I11+I12+$B$3)*0.27,0) | ... M14: =ROUND((M11+M12+$B$3)*0.27,0) | N14: =SUM(B14:M14)
A15: Marketing Spend (£) | B15: ='Marketing'!B14 | C15: ='Marketing'!C14 | D15: ='Marketing'!D14 | E15: 200 | F15: 200 | G15: 200 | H15: 200 | I15: 200 | J15: 200 | K15: 200 | L15: 200 | M15: 200 | N15: =SUM(B15:M15)
A16: Net Profit / Loss (£) | B16: =MATCH(TRUE,INDEX(B17:M17>0,0),0) | C16: =C13-C14-C15 | D16: =D13-D14-D15 | E16: =E13-E14-E15 | F16: =F13-F14-F15 | G16: =G13-G14-G15 | H16: =H13-H14-H15 | I16: =I13-I14-I15 | J16: =J13-J14-J15 | ... M16: =M13-M14-M15 | N16: =SUM(B16:M16)
A17: Cumulative Cash Flow (£) | B17: =B14+B15 | C17: =B17+C16 | D17: =C17+D16 | E17: =D17+E16 | F17: =E17+F16 | G17: =F17+G16 | H17: =G17+H16 | I17: =H17+I16 | J17: =I17+J16 | ... M17: =L17+M16 | N17: =M17
